{
  "device": {
    "vendor": "Dygma",
    "product": "Defy",
    "keyboardType": "wireless",
    "displayName": "Dygma Defy wireless",
    "urls": [
      {
        "name": "Homepage",
        "url": "https://www.dygma.com/defy/"
      }
    ]
  },
  "language": "fi-FI",
  "layerNames": [
    {
      "id": 0,
      "name": "Base"
    },
    {
      "id": 1,
      "name": "Symbols"
    },
    {
      "id": 2,
      "name": "Navigation"
    },
    {
      "id": 3,
      "name": "Mouse"
    },
    {
      "id": 4,
      "name": "F-keys"
    },
    {
      "id": 5,
      "name": "JetBrains"
    },
    {
      "id": 6,
      "name": "Gaming"
    },
    {
      "id": 7,
      "name": "Numpad"
    },
    {
      "id": 8,
      "name": "Transparent"
    },
    {
      "id": 9,
      "name": "No Key"
    }
  ],
  "keymap": [
    {
      "keyCode": 812,
      "label": "SPACE",
      "extraLabel": "C+A+"
    },
    {
      "keyCode": 30,
      "label": "1"
    },
    {
      "keyCode": 31,
      "label": "2"
    },
    {
      "keyCode": 32,
      "label": "3"
    },
    {
      "keyCode": 33,
      "label": "4"
    },
    {
      "keyCode": 34,
      "label": "5"
    },
    {
      "keyCode": 283,
      "label": "X",
      "extraLabel": "C+"
    },
    {
      "keyCode": 0,
      "label": "KEY",
      "extraLabel": "NO",
      "verbose": "Disabled"
    },
    {
      "keyCode": 0,
      "label": "KEY",
      "extraLabel": "NO",
      "verbose": "Disabled"
    },
    {
      "keyCode": 285,
      "label": "Z",
      "extraLabel": "C+"
    },
    {
      "keyCode": 35,
      "label": "6"
    },
    {
      "keyCode": 36,
      "label": "7"
    },
    {
      "keyCode": 37,
      "label": "8"
    },
    {
      "keyCode": 38,
      "label": "9"
    },
    {
      "keyCode": 39,
      "label": "0"
    },
    {
      "keyCode": 6166,
      "label": "S",
      "extraLabel": "S+O+"
    },
    {
      "keyCode": 43,
      "label": "TAB"
    },
    {
      "keyCode": 20,
      "label": "Q"
    },
    {
      "keyCode": 26,
      "label": "W"
    },
    {
      "keyCode": 9,
      "label": "F"
    },
    {
      "keyCode": 19,
      "label": "P"
    },
    {
      "keyCode": 10,
      "label": "G"
    },
    {
      "keyCode": 53981,
      "label": "Copy",
      "extraLabel": "SUPER"
    },
    {
      "keyCode": 0,
      "label": "KEY",
      "extraLabel": "NO",
      "verbose": "Disabled"
    },
    {
      "keyCode": 0,
      "label": "KEY",
      "extraLabel": "NO",
      "verbose": "Disabled"
    },
    {
      "keyCode": 53853,
      "label": "Next_",
      "extraLabel": "MACRO"
    },
    {
      "keyCode": 13,
      "label": "J"
    },
    {
      "keyCode": 15,
      "label": "L"
    },
    {
      "keyCode": 24,
      "label": "U"
    },
    {
      "keyCode": 28,
      "label": "Y"
    },
    {
      "keyCode": 51,
      "label": "Ö"
    },
    {
      "keyCode": 47,
      "label": "Å"
    },
    {
      "keyCode": 41,
      "label": "ESC"
    },
    {
      "keyCode": 49941,
      "label": "A",
      "extraLabel": "OS/"
    },
    {
      "keyCode": 49702,
      "label": "R",
      "extraLabel": "ALT/"
    },
    {
      "keyCode": 49191,
      "label": "S",
      "extraLabel": "CTRL/"
    },
    {
      "keyCode": 49448,
      "label": "T",
      "extraLabel": "SHIFT/"
    },
    {
      "keyCode": 7,
      "label": "D"
    },
    {
      "keyCode": 53980,
      "label": "Paste",
      "extraLabel": "SUPER"
    },
    {
      "keyCode": 0,
      "label": "KEY",
      "extraLabel": "NO",
      "verbose": "Disabled"
    },
    {
      "keyCode": 0,
      "label": "KEY",
      "extraLabel": "NO",
      "verbose": "Disabled"
    },
    {
      "keyCode": 53852,
      "label": "Prev_",
      "extraLabel": "MACRO"
    },
    {
      "keyCode": 11,
      "label": "H"
    },
    {
      "keyCode": 49442,
      "label": "N",
      "extraLabel": "SHIFT/"
    },
    {
      "keyCode": 49177,
      "label": "E",
      "extraLabel": "CTRL/"
    },
    {
      "keyCode": 49693,
      "label": "I",
      "extraLabel": "ALT/"
    },
    {
      "keyCode": 49955,
      "label": "O",
      "extraLabel": "OS/"
    },
    {
      "keyCode": 52,
      "label": "Ä"
    },
    {
      "keyCode": 40,
      "label": "ENTER"
    },
    {
      "keyCode": 29,
      "label": "Z"
    },
    {
      "keyCode": 27,
      "label": "X"
    },
    {
      "keyCode": 6,
      "label": "C"
    },
    {
      "keyCode": 25,
      "label": "V"
    },
    {
      "keyCode": 5,
      "label": "B"
    },
    {
      "keyCode": 0,
      "label": "KEY",
      "extraLabel": "NO",
      "verbose": "Disabled"
    },
    {
      "keyCode": 0,
      "label": "KEY",
      "extraLabel": "NO",
      "verbose": "Disabled"
    },
    {
      "keyCode": 0,
      "label": "KEY",
      "extraLabel": "NO",
      "verbose": "Disabled"
    },
    {
      "keyCode": 0,
      "label": "KEY",
      "extraLabel": "NO",
      "verbose": "Disabled"
    },
    {
      "keyCode": 14,
      "label": "K"
    },
    {
      "keyCode": 16,
      "label": "M"
    },
    {
      "keyCode": 54,
      "label": ","
    },
    {
      "keyCode": 55,
      "label": "."
    },
    {
      "keyCode": 56,
      "label": "-"
    },
    {
      "keyCode": 17498,
      "label": "7",
      "extraLabel": "LOCK"
    },
    {
      "keyCode": 2124,
      "label": "DEL",
      "extraLabel": "S+"
    },
    {
      "keyCode": 17494,
      "label": "3",
      "extraLabel": "LOCK"
    },
    {
      "keyCode": 44,
      "label": "SPACE"
    },
    {
      "keyCode": 17451,
      "label": "2",
      "extraLabel": "SHIFT"
    },
    {
      "keyCode": 17455,
      "label": "6",
      "extraLabel": "SHIFT"
    },
    {
      "keyCode": 0,
      "label": "KEY",
      "extraLabel": "NO",
      "verbose": "Disabled"
    },
    {
      "keyCode": 0,
      "label": "KEY",
      "extraLabel": "NO",
      "verbose": "Disabled"
    },
    {
      "keyCode": 0,
      "label": "KEY",
      "extraLabel": "NO",
      "verbose": "Disabled"
    },
    {
      "keyCode": 0,
      "label": "KEY",
      "extraLabel": "NO",
      "verbose": "Disabled"
    },
    {
      "keyCode": 17499,
      "label": "8",
      "extraLabel": "LOCK"
    },
    {
      "keyCode": 17499,
      "label": "8",
      "extraLabel": "LOCK"
    },
    {
      "keyCode": 17455,
      "label": "6",
      "extraLabel": "SHIFT"
    },
    {
      "keyCode": 40,
      "label": "ENTER"
    },
    {
      "keyCode": 42,
      "label": "BACKSPACE",
      "verbose": "Backspace"
    },
    {
      "keyCode": 76,
      "label": "DEL"
    },
    {
      "keyCode": 2124,
      "label": "DEL",
      "extraLabel": "S+"
    }
  ],
  "colormap": [
    0,
    0,
    0,
    0,
    0,
    0,
    2,
    0,
    0,
    0,
    0,
    0,
    0,
    2,
    0,
    0,
    0,
    0,
    0,
    0,
    2,
    0,
    0,
    0,
    0,
    0,
    0,
    1,
    0,
    0,
    0,
    0,
    15,
    15,
    12,
    0,
    0,
    0,
    0,
    0,
    0,
    2,
    0,
    0,
    0,
    0,
    0,
    0,
    2,
    0,
    0,
    0,
    0,
    0,
    0,
    2,
    0,
    0,
    0,
    0,
    0,
    0,
    1,
    0,
    0,
    0,
    0,
    0,
    0,
    12,
    15,
    15,
    15,
    15,
    15,
    15,
    15,
    15,
    15,
    15,
    15,
    15,
    15,
    15,
    15,
    15,
    15,
    15,
    15,
    15,
    15,
    15,
    15,
    15,
    15,
    15,
    15,
    15,
    15,
    15,
    15,
    15,
    15,
    15,
    15,
    15,
    15,
    15,
    15,
    15,
    15,
    15,
    15,
    15,
    15,
    15,
    15,
    15,
    15,
    15,
    15,
    15,
    15,
    15,
    15,
    15,
    15,
    15,
    15,
    15,
    15,
    15,
    15,
    15,
    15,
    15,
    15,
    15,
    15,
    15,
    15,
    15,
    15,
    15,
    15,
    15,
    15,
    15,
    15,
    15,
    15,
    15,
    15,
    15,
    15,
    15,
    15,
    15,
    15,
    15,
    15,
    15,
    15,
    15,
    15,
    15,
    15,
    15,
    15,
    15,
    15,
    15,
    15,
    15,
    15,
    15,
    15,
    3
  ],
  "palette": [
    {
      "r": 255,
      "g": 0,
      "b": 255,
      "rgb": "rgb(255, 0, 255)"
    },
    {
      "r": 255,
      "g": 0,
      "b": 100,
      "rgb": "rgb(255, 0, 100)"
    },
    {
      "r": 100,
      "g": 0,
      "b": 255,
      "rgb": "rgb(100, 0, 255)"
    },
    {
      "r": 255,
      "g": 0,
      "b": 0,
      "rgb": "rgb(255, 0, 0)"
    },
    {
      "r": 0,
      "g": 255,
      "b": 0,
      "rgb": "rgb(0, 255, 0)"
    },
    {
      "r": 0,
      "g": 0,
      "b": 255,
      "rgb": "rgb(0, 0, 255)"
    },
    {
      "r": 0,
      "g": 255,
      "b": 255,
      "rgb": "rgb(0, 255, 255)"
    },
    {
      "r": 255,
      "g": 180,
      "b": 0,
      "rgb": "rgb(255, 180, 0)"
    },
    {
      "r": 255,
      "g": 19,
      "b": 254,
      "rgb": "rgb(255, 19, 254)"
    },
    {
      "r": 255,
      "g": 255,
      "b": 255,
      "rgb": "rgb(255, 255, 255)"
    },
    {
      "r": 214,
      "g": 129,
      "b": 255,
      "rgb": "rgb(214, 129, 255)"
    },
    {
      "r": 255,
      "g": 255,
      "b": 255,
      "rgb": "rgb(255, 255, 255)"
    },
    {
      "r": 0,
      "g": 0,
      "b": 0,
      "rgb": "rgb(0, 0, 0)"
    },
    {
      "r": 0,
      "g": 0,
      "b": 0,
      "rgb": "rgb(0, 0, 0)"
    },
    {
      "r": 0,
      "g": 0,
      "b": 0,
      "rgb": "rgb(0, 0, 0)"
    },
    {
      "r": 0,
      "g": 0,
      "b": 0,
      "rgb": "rgb(0, 0, 0)"
    }
  ]
}